instate/__init__.py
instate/_utils.py
instate/constants.py
instate/data/instate_unique_ln_state_prop_v1.csv.gz
instate/data/lastname_langs_india.csv.tar.gz
instate/data/lastname_langs_india_top3.csv.tar.gz
instate/data/state_lang_labels.pt
instate/data/state_to_languages.csv
instate/electoral.py
instate/nnets.py
instate/predict.py
instate/py.typed
instate-1.1.0.dist-info/WHEEL
instate-1.1.0.dist-info/METADATA
instate-1.1.0.dist-info/RECORD
