Metadata-Version: 2.3
Name: instate
Version: 1.1.0
Summary: Instate: predict the state of residence from last name
Keywords: predict,state,residence,last name
Author: Atul Dhingra, Gaurav Sood, Rajashekar Chintalapati
Author-email: Atul Dhingra <dhingra.atul92@gmail.com>, Gaurav Sood <gsood07@gmail.com>, Rajashekar Chintalapati <rajshekar.ch@gmail.com>
License: MIT
Classifier: Development Status :: 3 - Alpha
Classifier: Intended Audience :: Developers
Classifier: License :: OSI Approved :: MIT License
Classifier: Programming Language :: Python :: 3.11
Classifier: Programming Language :: Python :: 3.12
Classifier: Programming Language :: Python :: 3.13
Classifier: Topic :: Scientific/Engineering :: Information Analysis
Classifier: Topic :: Software Development :: Libraries :: Python Modules
Classifier: Topic :: Utilities
Requires-Dist: pandas>=1.5.0
Requires-Dist: numpy>=1.21.0,<2.0.0
Requires-Dist: torch>=2.0.0
Requires-Dist: levenshtein>=0.20.0
Requires-Dist: requests>=2.25.0
Requires-Dist: tqdm>=4.64.0
Requires-Python: >=3.11, <3.14
Project-URL: Bug Tracker, https://github.com/appeler/instate/issues
Project-URL: Homepage, https://github.com/appeler/instate
Project-URL: Repository, https://github.com/appeler/instate
